{
  "pointeShoes": [
    {
      "name": "alpha",
      "brand": "Bloch",
      "feetType": "Egyptian",
      "strength": "Strong",
      "toesLength": "Long",
      "arcProfile": "High",
      "width": "Narrow",
      "id": 1
    },
    {
      "name": "Elite",
      "brand": "Grishko",
      "feetType": "Giselle",
      "strength": "Medium",
      "toesLength": "Short",
      "arcProfile": "Low",
      "width": "Wide",
      "id": 2
    },
    {
      "name": "Balance",
      "brand": "Bloch",
      "feetType": "Giselle",
      "strength": "Low",
      "toesLength": "Short",
      "arcProfile": "Low",
      "width": "Wide",
      "id": 3
    },
    {
      "name": "Recital",
      "brand": "Sansh",
      "feetType": "Giselle",
      "strength": "Medium",
      "toesLength": "Medium",
      "arcProfile": "Medium",
      "width": "Medium",
      "id": 4
    },
    {
      "name": "Contempor",
      "brand": "Capezio",
      "feetType": "Greek",
      "strength": "Low",
      "toesLength": "Medium",
      "arcProfile": "Low",
      "width": "Medium",
      "id": 5
    }
  ]
}